django_docker_engine/VERSION.txt
django_docker_engine/__init__.py
django_docker_engine/docker_utils.py
django_docker_engine/historian.py
django_docker_engine/please-wait.html
django_docker_engine/proxy.py
django_docker_engine/container_managers/__init__.py
django_docker_engine/container_managers/base.py
django_docker_engine/container_managers/docker_engine.py
django_docker_engine/middleware/__init__.py
django_docker_engine/middleware/hostname_routing.py
django_docker_engine-0.1.4.dist-info/LICENSE
django_docker_engine-0.1.4.dist-info/METADATA
django_docker_engine-0.1.4.dist-info/WHEEL
django_docker_engine-0.1.4.dist-info/top_level.txt
django_docker_engine-0.1.4.dist-info/RECORD
